objp/__init__.py
objp/base.py
objp/const.py
objp/o2p.py
objp/p2o.py
objp/util.py
objp/data/ObjP.h
objp/data/ObjP.m
objp-1.3.2.dist-info/DESCRIPTION.rst
objp-1.3.2.dist-info/METADATA
objp-1.3.2.dist-info/RECORD
objp-1.3.2.dist-info/WHEEL
objp-1.3.2.dist-info/metadata.json
objp-1.3.2.dist-info/top_level.txt
