Metadata-Version: 2.0
Name: objp
Version: 1.3.2
Summary: Python<-->Objective-C bridge with a code generation approach
Home-page: https://github.com/hsoft/objp
Author: Hardcoded Software
Author-email: hsoft@hardcoded.net
License: BSD License
Platform: UNKNOWN
Classifier: Intended Audience :: Developers
Classifier: License :: OSI Approved :: BSD License
Classifier: Programming Language :: Python :: 3
Classifier: Programming Language :: Python :: 3.2
Classifier: Programming Language :: Python :: 3.3
Classifier: Programming Language :: Python :: 3.4
Classifier: Programming Language :: Python :: 3.5
